tidal_mcp_server/__init__.py
tidal_mcp_server/__main__.py
tidal_mcp_server/client.py
tidal_mcp_server/server.py
tidal_mcp_server-0.1.1.dist-info/METADATA
tidal_mcp_server-0.1.1.dist-info/WHEEL
tidal_mcp_server-0.1.1.dist-info/entry_points.txt
tidal_mcp_server-0.1.1.dist-info/RECORD
